MG_Managers/AnyLogicRLAgents.py
MG_Managers/ESM_AGENTS.py
MG_Managers/__init__.py
_DATAGENERATORS/_DataGenerators.py
_DATAGENERATORS/__init__.py
_RLCoach_ENVS/_GRID_ENVs.py
_RLCoach_ENVS/__init__.py
rl_mgm-0.0.4.dist-info/LICENSE
rl_mgm-0.0.4.dist-info/METADATA
rl_mgm-0.0.4.dist-info/WHEEL
rl_mgm-0.0.4.dist-info/top_level.txt
rl_mgm-0.0.4.dist-info/RECORD
