Metadata-Version: 2.1
Name: rl-mgm
Version: 0.0.4
Summary: A Python module for reinforcement learning based energy management system tools
Author-email: Gerald Jones <gjones2@vols.utk.edu>
Maintainer-email: Gerald Jones <gjones2@vols.utk.edu>
License: Apache License
Keywords: reinforcement learning,energy management system,building energy management
Requires-Python: >=3.8
License-File: LICENSE
Requires-Dist: setuptools
Requires-Dist: setuptools-scm
Requires-Dist: wheel
Requires-Dist: numpy
Requires-Dist: torch
Requires-Dist: matplotlib
Requires-Dist: joblib
Requires-Dist: pandas
Requires-Dist: scipy
Requires-Dist: scikit-learn
